README.md
setup.py
nn/__init__.py
nn/core.py
nn/layers.py
nn/ops.py
nn/optimizers.py
nn/utils.py
nn.egg-info/PKG-INFO
nn.egg-info/SOURCES.txt
nn.egg-info/dependency_links.txt
nn.egg-info/not-zip-safe
nn.egg-info/requires.txt
nn.egg-info/top_level.txt